Metadata-Version: 2.1
Name: sortify
Version: 1.2.1
Summary: A Python package containing implementation of various sorting algorithms.
Home-page: https://github.com/amansharma2910/Sortify
Author: Aman Sharma
Author-email: amansharma2910@gmail.com
License: UNKNOWN
Platform: UNKNOWN
